{
  "cards": [
    {
      "id": 1,
      "status": "to do",
      "items": [
        {
          "id": 1,
          "numberCard": "KD-1",
          "description": "write new text",
          "statusCard": "to do"
        }
      ]
    },
    {
      "id": 2,
      "status": "progress",
      "items": [
        {
          "id": 2,
          "numberCard": "KD-2",
          "description": "write new table",
          "statusCard": "progress"
        }
      ]
    },
    {
      "id": 3,
      "status": "review",
      "items": [
        {
          "id": 3,
          "numberCard": "KD-3",
          "description": "write new something",
          "statusCard": "review"
        }
      ]
    },
    {
      "id": 4,
      "status": "done",
      "items": [
        {
          "id": 4,
          "numberCard": "KD-4",
          "description": "write new apple",
          "statusCard": "done"
        }
      ]
    }
  ]
}